chyk/__init__.py
chyk-0.2.0.7.dist-info/LICENSE.txt
chyk-0.2.0.7.dist-info/METADATA
chyk-0.2.0.7.dist-info/WHEEL
chyk-0.2.0.7.dist-info/top_level.txt
chyk-0.2.0.7.dist-info/RECORD
