Metadata-Version: 2.1
Name: chyk
Version: 0.2.0.7
Summary: Custom Package Loader
Author: Chickenfysh
Author-email: iamchicken_3401@outlook.com
Classifier: Programming Language :: Python :: 3
Classifier: License :: OSI Approved :: MIT License
Classifier: Operating System :: OS Independent
License-File: LICENSE.txt
